[
    {
        "id": 1,
        "name": "Wheat Atta",
        "image": "./grocery/1.jpg",
        "price": "₹120.00",
        "description": "High-quality wheat atta for all your baking needs.",
        "detailImage": "grocery-wheat-atta-detail.jpg"
    },
    {
        "id": 2,
        "name": "Basmati Rice",
        "image": "./grocery/2.jpg",
        "price": "₹250.00",
        "description": "Premium basmati rice with a delightful aroma.",
        "detailImage": "grocery-basmati-rice-detail.jpg"
    },
    {
        "id": 3,
        "name": "Red Lentils (Masoor Dal)",
        "image": "./grocery/3.jpg",
        "price": "₹180.00",
        "description": "Nutritious red lentils for a variety of dishes.",
        "detailImage": "grocery-red-lentils-detail.jpg"
    },
    {
        "id": 4,
        "name": "Toor Dal",
        "image": "./grocery/4.jpg",
        "price": "₹220.00",
        "description": "High-quality toor dal for a rich, flavorful meal.",
        "detailImage": "grocery-toor-dal-detail.jpg"
    },
    {
        "id": 5,
        "name": "Chana Dal",
        "image": "./grocery/5.jpg",
        "price": "₹200.00",
        "description": "Split chickpeas (chana dal) with great taste and texture.",
        "detailImage": "grocery-chana-dal-detail.jpg"
    },
    {
        "id": 6,
        "name": "Maida",
        "image": "./grocery/6.jpg",
        "price": "₹130.00",
        "description": "Fine quality maida for baking and cooking.",
        "detailImage": "grocery-maida-detail.jpg"
    },
    {
        "id": 7,
        "name": "Sunflower Oil",
        "image": "./grocery/7.jpg",
        "price": "₹280.00",
        "description": "Pure sunflower oil for cooking and frying.",
        "detailImage": "grocery-sunflower-oil-detail.jpg"
    },
    {
        "id": 8,
        "name": "Mustard Oil",
        "image": "./grocery/8.jpg",
        "price": "₹250.00",
        "description": "Authentic mustard oil with a strong flavor.",
        "detailImage": "grocery-mustard-oil-detail.jpg"
    },
    {
        "id": 9,
        "name": "Vegetable Oil",
        "image": "./grocery/9.jpg",
        "price": "₹220.00",
        "description": "Versatile vegetable oil for daily cooking.",
        "detailImage": "grocery-vegetable-oil-detail.jpg"
    }
]
